gammarer/aws_ec2_instance_running_scheduler/__init__.py
gammarer/aws_ec2_instance_running_scheduler/py.typed
gammarer/aws_ec2_instance_running_scheduler/_jsii/__init__.py
gammarer/aws_ec2_instance_running_scheduler/_jsii/aws-ec2-instance-running-schedule-stack@2.0.0.jsii.tgz
gammarer.aws_ec2_instance_running_scheduler-2.0.0.dist-info/LICENSE
gammarer.aws_ec2_instance_running_scheduler-2.0.0.dist-info/METADATA
gammarer.aws_ec2_instance_running_scheduler-2.0.0.dist-info/WHEEL
gammarer.aws_ec2_instance_running_scheduler-2.0.0.dist-info/top_level.txt
gammarer.aws_ec2_instance_running_scheduler-2.0.0.dist-info/RECORD
